{"_default": {"1": {"url": "https://sfbay.craigslist.org/sfc/apa/d/sleek-bd-ba-flat-parking/6231107885.html", "kind": "apa", "location": "https://maps.google.com/?q=loc%3A+%38%39%39+Valencia+San+Francisco+CA+US", "price": "$7995", "available": "available jul 1", "posted": "2017-07-22 10:38am", "transit": 2, "bicycling": 10, "stanford": 69}, "2": {"url": "https://sfbay.craigslist.org/sfc/apa/6219973416.html", "kind": "apa", "location": "https://maps.google.com/maps/preview/@37.718834,-122.397479,16z", "price": "$2600", "available": "available aug 1", "posted": "2017-07-14  5:41pm", "transit": 33, "bicycling": 25, "stanford": 75}, "3": {"url": "https://sfbay.craigslist.org/sfc/apa/d/walking-distance-to-sfsu/6231175816.html", "kind": "apa", "location": "https://maps.google.com/?q=loc%3A+Vernon+at+Garfield+San+Francisco+CA+US", "price": "$2200", "available": "available aug 1", "posted": "2017-07-22 11:17am", "transit": 45, "bicycling": 37, "stanford": 111}, "4": {"url": "http://sfbay.craigslist.org/sfc/apa/6231028259.html", "kind": "apa", "location": "https://maps.google.com/?q=loc%3A+%32%36%30+%32%36th+Avenue+at+California+Street+San+Francisco+CA+US", "price": "$2700", "available": "available jul 22", "posted": "2017-07-22  9:53am", "transit": 69, "bicycling": 122, "stanford": 31}, "5": {"url": "http://sfbay.craigslist.org/sfc/apa/6231006372.html", "kind": "apa", "location": "https://maps.google.com/?q=loc%3A+%31%37%35+tunnel+ave+San+Francisco+CA+US", "price": "$3000", "available": "available jul 22", "posted": "2017-07-22  9:40am", "transit": 30, "bicycling": 29, "stanford": 65}, "6": {"url": "http://sfbay.craigslist.org/sfc/apa/6230845008.html", "kind": "apa", "location": "https://maps.google.com/?q=loc%3A+%33%35%37%35+Keith+Street+San+Francisco+CA+US", "price": "$2600", "available": "available jul 22", "posted": "2017-07-22  8:05am", "transit": 31, "bicycling": 21, "stanford": 85}, "7": {"url": "http://sfbay.craigslist.org/sfc/apa/6205599768.html", "kind": "apa", "location": "https://maps.google.com/?q=loc%3A+%39%34%36+Geary+San+Francisco+CA+US", "price": "$2995", "available": "available may 30", "posted": "2017-07-05  9:09am", "transit": 19, "bicycling": 15, "stanford": 58}, "8": {"url": "http://sfbay.craigslist.org/sfc/apa/6202235685.html", "kind": "apa", "location": "https://maps.google.com/?q=loc%3A+%36TH+AVE+at+Cabrillo%2FFulton+San+Francisco+CA+US", "price": "$2800", "available": "available jul 19", "posted": "2017-07-02  3:47pm", "transit": null, "bicycling": null, "stanford": null}, "9": {"url": "http://sfbay.craigslist.org/sfc/apa/6209917609.html", "kind": "apa", "location": "https://maps.google.com/?q=loc%3A+San+Diego+at+Parkview++CA+US", "price": "$2795", "available": "available jul 10", "posted": "2017-07-08  4:25am", "transit": 40, "bicycling": 41, "stanford": 87}, "10": {"url": "http://sfbay.craigslist.org/sfc/apa/6230511077.html", "kind": "apa", "location": "https://maps.google.com/?q=loc%3A+%39%30%30+Rivera+Street+San+Francisco+CA+US", "price": "$2820", "available": "available jul 22", "posted": "2017-07-22 12:38am", "transit": 45, "bicycling": 42, "stanford": 119}, "11": {"url": "http://sfbay.craigslist.org/sfc/apa/6230495386.html", "kind": "apa", "location": "https://maps.google.com/maps/preview/@37.719500,-122.441100,16z", "price": "$2500", "available": "available jul 21", "posted": "2017-07-21 11:55pm", "transit": 36, "bicycling": 31, "stanford": 91}, "12": {"url": "http://sfbay.craigslist.org/sfc/apa/6227235729.html", "kind": "apa", "location": "https://maps.google.com/?q=loc%3A+Faxon+at+Ocean+San+Francisco+CA+US", "price": "$2700", "available": "available sep 15", "posted": "2017-07-19  4:58pm", "transit": 45, "bicycling": 32, "stanford": 99}, "13": {"url": "http://sfbay.craigslist.org/sfc/apa/6230454678.html", "kind": "apa", "location": "https://maps.google.com/?q=loc%3A+london+at+brazil+sf+CA+US", "price": "$3000", "available": "available jul 23", "posted": "2017-07-21 10:27pm", "transit": 44, "bicycling": 29, "stanford": 97}, "14": {"url": "http://sfbay.craigslist.org/sfc/apa/6230458207.html", "kind": "apa", "price": "$3000", "available": "available sep 10", "posted": "2017-07-21 10:33pm"}, "15": {"url": "http://sfbay.craigslist.org/sfc/apa/6216528393.html", "kind": "apa", "location": "https://maps.google.com/?q=loc%3A+%32%35%33%30+%34%36th+Avenue+at+Ulloa+St+San+Francisco+CA+US", "price": "$2495", "available": "available aug 1", "posted": "2017-07-12 12:14pm", "transit": 69, "bicycling": 122, "stanford": 31}, "16": {"url": "http://sfbay.craigslist.org/sfc/apa/6218687138.html", "kind": "apa", "location": "https://maps.google.com/?q=loc%3A+Miramar+at+Monterey+San+Francisco+CA+US", "price": "$2880", "available": "available jul 20", "posted": "2017-07-13  9:48pm", "transit": 39, "bicycling": 28, "stanford": 95}, "17": {"url": "http://sfbay.craigslist.org/sfc/apa/6230432186.html", "kind": "apa", "location": "https://maps.google.com/?q=loc%3A+%32%32+Leona+Terrace+San+Francisco+CA+US", "price": "$2395", "available": "available jul 22", "posted": "2017-07-21  9:47pm", "transit": 38, "bicycling": 20, "stanford": 111}, "18": {"url": "http://sfbay.craigslist.org/sfc/apa/6221539430.html", "kind": "apa", "location": "https://maps.google.com/?q=loc%3A+%31%34%30%30+%34%37th+Avenue+at+Judah+San+Francisco+CA+US", "price": "$2990", "available": "available jul 18", "posted": "2017-07-15  8:00pm", "transit": 71, "bicycling": 122, "stanford": 32}, "19": {"url": "http://sfbay.craigslist.org/sfc/apa/6221316163.html", "kind": "apa", "location": "https://maps.google.com/?q=loc%3A+%32%30th+at+taraval+san+francisco+CA+US", "price": "$2150", "available": "available jul 15", "posted": "2017-07-15  3:55pm", "transit": 37, "bicycling": 17, "stanford": 99}, "20": {"url": "http://sfbay.craigslist.org/sfc/apa/6230420014.html", "kind": "apa", "location": "https://maps.google.com/?q=loc%3A+Clay+at+Mason+San+Francisco+CA+US", "price": "$2500", "available": "available jul 21", "posted": "2017-07-21  9:27pm", "transit": 30, "bicycling": 18, "stanford": 99}, "21": {"url": "http://sfbay.craigslist.org/sby/apa/6230377124.html", "kind": "apa", "price": "$1168", "available": "available jul 21", "posted": "2017-07-21  8:24pm"}, "22": {"url": "http://sfbay.craigslist.org/sfc/apa/6222568137.html", "kind": "apa", "location": "https://maps.google.com/?q=loc%3A+Alemany+at+Ocean+San+Francisco+CA+US", "price": "$2100", "available": "available aug 1", "posted": "2017-07-16  3:19pm", "transit": 37, "bicycling": 29, "stanford": 94}, "23": {"url": "http://sfbay.craigslist.org/sfc/apa/6191009131.html", "kind": "apa", "location": "https://maps.google.com/?q=loc%3A+%36th+Ave%2E+at+Cabrillo%2FFulton+San+Francisco+CA+US", "price": "$2800", "available": "available jul 29", "posted": "2017-06-24  9:46am", "transit": null, "bicycling": null, "stanford": null}, "24": {"url": "http://sfbay.craigslist.org/sfc/apa/6223663644.html", "kind": "apa", "location": "https://maps.google.com/?q=loc%3A+%31%34th+Ave+at+Anza+San+Francisco+CA+US", "price": "$2500", "available": "available jul 17", "posted": "2017-07-17 11:16am", "transit": 61, "bicycling": 43, "stanford": 162}, "25": {"url": "http://sfbay.craigslist.org/sfc/apa/6230303399.html", "kind": "apa", "location": "https://maps.google.com/?q=loc%3A+persia+at+madrid+san+francisco+CA+US", "price": "$2395", "available": "available aug 1", "posted": "2017-07-21  6:58pm", "transit": 34, "bicycling": 28, "stanford": 94}, "26": {"url": "http://sfbay.craigslist.org/sfc/apa/6230130500.html", "kind": "apa", "location": "https://maps.google.com/maps/preview/@37.797400,-122.400100,16z", "price": "$580", "available": "available jul 21", "posted": "2017-07-21  4:19pm", "transit": 28, "bicycling": 19, "stanford": 106}, "27": {"url": "http://sfbay.craigslist.org/sfc/apa/6212058819.html", "kind": "apa", "location": "https://maps.google.com/?q=loc%3A+%31%30%36+San+Jose+Avenue+San+Francisco+CA+US", "price": "$2980", "available": "available jul 17", "posted": "2017-07-09  1:52pm", "transit": 30, "bicycling": 13, "stanford": 93}, "28": {"url": "http://sfbay.craigslist.org/sfc/apa/6208748347.html", "kind": "apa", "location": "https://maps.google.com/?q=loc%3A+%36%34%36+%33%35th+Ave+at+Balboa+St+San+Francisco+CA+US", "price": "$2200", "available": "available jul 9", "posted": "2017-07-07  9:18am", "transit": 52, "bicycling": 38, "stanford": 120}, "29": {"url": "http://sfbay.craigslist.org/sfc/apa/6230093264.html", "kind": "apa", "location": "https://maps.google.com/maps/preview/@37.719500,-122.441100,16z", "price": "$2200", "available": "available aug 1", "posted": "2017-07-21  3:49pm", "transit": 36, "bicycling": 31, "stanford": 91}, "30": {"url": "http://sfbay.craigslist.org/sfc/apa/6224099208.html", "kind": "apa", "location": "https://maps.google.com/maps/preview/@37.744100,-122.486300,16z", "price": "$2950", "available": "available sep 1", "posted": "2017-07-17  3:45pm", "transit": 42, "bicycling": 43, "stanford": 119}, "31": {"url": "http://sfbay.craigslist.org/sfc/apa/6209569616.html", "kind": "apa", "location": "https://maps.google.com/?q=loc%3A+%37%39%30+%34%33rd+Ave+at+Cabrillo+St%2E+SAN+FRANCISCO+CA+US", "price": "$2200", "available": "available jul 10", "posted": "2017-07-07  6:06pm", "transit": 50, "bicycling": 37, "stanford": 122}, "32": {"url": "http://sfbay.craigslist.org/sfc/apa/6212566899.html", "kind": "apa", "location": "https://maps.google.com/?q=loc%3A+Felton++CA+US", "price": "$2800", "available": "available jun 30", "posted": "2017-07-09 10:16pm", "transit": 245, "bicycling": 473, "stanford": 185}, "33": {"url": "http://sfbay.craigslist.org/sfc/apa/6230001443.html", "kind": "apa", "location": "https://maps.google.com/?q=loc%3A+%31%37th+St+at+Church+San+Francisco+CA+US", "price": "$2300", "available": "available aug 20", "posted": "2017-07-21  2:41pm", "transit": 82, "bicycling": null, "stanford": 150}, "34": {"url": "http://sfbay.craigslist.org/sfc/apa/6229947701.html", "kind": "apa", "location": "https://maps.google.com/maps/preview/@37.719298,-122.390020,16z", "price": "$2400", "available": "available aug 1", "posted": "2017-07-21  2:04pm", "transit": 38, "bicycling": 25, "stanford": 86}, "35": {"url": "http://sfbay.craigslist.org/sfc/apa/6229927496.html", "kind": "apa", "location": "https://maps.google.com/?q=loc%3A+%34%32+Farragut+Ave+San+Francisco+CA+US", "price": "$2800", "available": "available aug 1", "posted": "2017-07-21  1:51pm", "transit": 49, "bicycling": 34, "stanford": 103}, "36": {"url": "http://sfbay.craigslist.org/sfc/apa/6229848419.html", "kind": "apa", "location": "https://maps.google.com/?q=loc%3A+%31+Wattson+Pl+San+Francisco+CA+US", "price": "$2995", "available": "available jul 21", "posted": "2017-07-21  1:00pm", "transit": 42, "bicycling": 30, "stanford": 95}, "37": {"url": "http://sfbay.craigslist.org/sfc/apa/6229604656.html", "kind": "apa", "location": "https://maps.google.com/maps/preview/@37.781300,-122.416700,16z", "price": "$795", "available": "available jul 21", "posted": "2017-07-21 10:33am", "transit": 13, "bicycling": 8, "stanford": 95}, "38": {"url": "http://sfbay.craigslist.org/sfc/apa/6229691330.html", "kind": "apa", "location": "https://maps.google.com/?q=loc%3A+%33%34th+Ave+at+Geary+St+San+Francisco+CA+US", "price": "$2800", "available": "available jul 15", "posted": "2017-07-21 11:24am", "transit": 61, "bicycling": 43, "stanford": 162}, "39": {"url": "http://sfbay.craigslist.org/sfc/apa/6229673240.html", "kind": "apa", "location": "https://maps.google.com/?q=loc%3A+london+at+brazil+sf+CA+US", "price": "$3000", "available": "available aug 1", "posted": "2017-07-21 11:13am", "transit": 42, "bicycling": 29, "stanford": 99}, "40": {"url": "http://sfbay.craigslist.org/sfc/apa/6194125410.html", "kind": "apa", "location": "https://maps.google.com/?q=loc%3A+%32%37%31%34%2DA+Sutter+st+san+francisco+CA+US", "price": "$2990", "available": "available jul 1", "posted": "2017-06-26  3:35pm", "transit": null, "bicycling": null, "stanford": null}, "41": {"url": "http://sfbay.craigslist.org/sfc/apa/6229633545.html", "kind": "apa", "location": "https://maps.google.com/?q=loc%3A+%34%36th+Avenue+at+Vicente+San+Francisco+CA+US", "price": "$2380", "available": "available jul 21", "posted": "2017-07-21 10:50am", "transit": 69, "bicycling": 122, "stanford": 31}, "42": {"url": "http://sfbay.craigslist.org/sfc/apa/6219973416.html", "kind": "apa", "location": "https://maps.google.com/maps/preview/@37.718834,-122.397479,16z", "price": "$2600", "available": "available aug 1", "posted": "2017-07-14  5:41pm", "transit": 37, "bicycling": 25, "stanford": 75}, "43": {"url": "http://sfbay.craigslist.org/sfc/apa/6223816017.html", "kind": "apa", "location": "https://maps.google.com/?q=loc%3A+%34%36th+Ave%2E+at+Balboa+St%2E+San+Francisco+CA+US", "price": "$2100", "available": "available jul 17", "posted": "2017-07-17 12:43pm", "transit": 69, "bicycling": 122, "stanford": 31}, "44": {"url": "http://sfbay.craigslist.org/sfc/apa/6226530501.html", "kind": "apa", "location": "https://maps.google.com/?q=loc%3A+%34%36th+Ave%2E+at+Balboa+St%2E+San+Francisco+CA+US", "price": "$2100", "available": "available jul 19", "posted": "2017-07-19  9:23am", "transit": 69, "bicycling": 122, "stanford": 31}, "45": {"url": "http://sfbay.craigslist.org/sfc/apa/6229570124.html", "kind": "apa", "location": "https://maps.google.com/?q=loc%3A+%34%36th+Ave%2E+at+Balboa+St%2E+San+Francisco+CA+US", "price": "$2100", "available": "available jul 21", "posted": "2017-07-21 10:13am", "transit": 69, "bicycling": 122, "stanford": 31}, "46": {"url": "http://sfbay.craigslist.org/sfc/apa/6222942562.html", "kind": "apa", "location": "https://maps.google.com/maps/preview/@37.719298,-122.390020,16z", "price": "$2400", "available": "available aug 1", "posted": "2017-07-16 10:21pm", "transit": 38, "bicycling": 25, "stanford": 86}, "47": {"url": "http://sfbay.craigslist.org/sfc/apa/6229504498.html", "kind": "apa", "location": "https://maps.google.com/?q=loc%3A+%33%35th+Avenue+at+Balboa+San+Francisco+CA+US", "price": "$2900", "available": "available jun 26", "posted": "2017-07-21  9:35am", "transit": 53, "bicycling": 38, "stanford": 120}, "48": {"url": "http://sfbay.craigslist.org/sfc/apa/6218329729.html", "kind": "apa", "location": "https://maps.google.com/?q=loc%3A+%36th+Ave%2E+at+Cabrillo%2FFulton+San+Francisco+CA+US", "price": "$2800", "available": "available jul 21", "posted": "2017-07-13  3:33pm", "transit": null, "bicycling": null, "stanford": null}, "49": {"url": "http://sfbay.craigslist.org/sfc/apa/6229334924.html", "kind": "apa", "location": "https://maps.google.com/?q=loc%3A+Jordan+Ave+at+Euclid+Ave+San+Francisco+CA+US", "price": "$2750", "available": "available aug 15", "posted": "2017-07-21  7:56am", "transit": 43, "bicycling": 27, "stanford": 117}, "50": {"url": "http://sfbay.craigslist.org/sfc/apa/6211231253.html", "kind": "apa", "location": "https://maps.google.com/?q=loc%3A+Orizaba+Avenue+at+Randolph+San+Francisco+CA+US", "price": "$2995", "available": "available aug 1", "posted": "2017-07-08 10:38pm", "transit": 42, "bicycling": 42, "stanford": 100}, "51": {"url": "http://sfbay.craigslist.org/sfc/apa/6213951507.html", "kind": "apa", "location": "https://maps.google.com/?q=loc%3A+Noriega+at+%32%32nd+SF+CA+US", "price": "$2700", "available": "available jul 15", "posted": "2017-07-10  6:07pm", "transit": 61, "bicycling": 39, "stanford": 120}, "52": {"url": "http://sfbay.craigslist.org/sfc/apa/6208248917.html", "kind": "apa", "location": "https://maps.google.com/?q=loc%3A+%37%31%30+%31%39th+Ave+at+Cabrillo+St+San+Francisco+CA+US", "price": "$3000", "available": "available jul 6", "posted": "2017-07-07 12:30am", "transit": 56, "bicycling": 44, "stanford": 121}, "53": {"url": "http://sfbay.craigslist.org/sfc/apa/6188170882.html", "kind": "apa", "location": "https://maps.google.com/maps/preview/@37.719541,-122.410183,16z", "price": "$1300", "available": "available aug 1", "posted": "2017-06-22 10:31am", "transit": 35, "bicycling": 31, "stanford": 85}, "54": {"url": "http://sfbay.craigslist.org/sfc/apa/6228992261.html", "kind": "apa", "location": "https://maps.google.com/?q=loc%3A+%33%35%37%35+Keith+Street+San+Francisco+CA+US", "price": "$2600", "available": "available aug 1", "posted": "2017-07-20 10:44pm", "transit": 19, "bicycling": 21, "stanford": 85}, "55": {"url": "http://sfbay.craigslist.org/sfc/apa/6218466264.html", "kind": "apa", "location": "https://maps.google.com/maps/preview/@37.725040,-122.403638,16z", "price": "$2250", "available": "available jul 8", "posted": "2017-07-13  5:24pm", "transit": 25, "bicycling": 26, "stanford": 76}, "56": {"url": "http://sfbay.craigslist.org/sfc/apa/6225845913.html", "kind": "apa", "location": "https://maps.google.com/maps/preview/@37.725040,-122.403660,16z", "price": "$2250", "available": "available jul 18", "posted": "2017-07-18  6:47pm", "transit": 25, "bicycling": 26, "stanford": 75}, "57": {"url": "http://sfbay.craigslist.org/sfc/apa/6223681482.html", "kind": "apa", "location": "https://maps.google.com/?q=loc%3A+Rae+at+Farragut+San+Francisco+CA+US", "price": "$2700", "available": "available jun 1", "posted": "2017-07-17 11:26am", "transit": 50, "bicycling": 33, "stanford": 105}, "58": {"url": "http://sfbay.craigslist.org/sfc/apa/6228970779.html", "kind": "apa", "location": "https://maps.google.com/?q=loc%3A+Navajo+Ave%2E+at+Delano+St%2E+San+Francisco+CA+US", "price": "$2800", "available": "available jul 20", "posted": "2017-07-20 10:00pm", "transit": 31, "bicycling": 31, "stanford": 86}, "59": {"url": "http://sfbay.craigslist.org/sfc/apa/6228951676.html", "kind": "apa", "price": "$2200", "available": "available jul 25", "posted": "2017-07-20  9:27pm"}, "60": {"url": "http://sfbay.craigslist.org/sfc/apa/6228911234.html", "kind": "apa", "location": "https://maps.google.com/?q=loc%3A+%32%35%39+Polaris+Way+Daly+City+CA+US", "price": "$2000", "available": "available jul 20", "posted": "2017-07-20  8:29pm", "transit": 59, "bicycling": 35, "stanford": 101}, "61": {"url": "http://sfbay.craigslist.org/sfc/apa/6228893548.html", "kind": "apa", "location": "https://maps.google.com/?q=loc%3A+Market+Street+at+Romain+San+Francisco+CA+US", "price": "$1750", "available": "available jul 20", "posted": "2017-07-20  8:07pm", "transit": 37, "bicycling": 21, "stanford": 100}, "62": {"url": "http://sfbay.craigslist.org/sfc/apa/6228892205.html", "kind": "apa", "location": "https://maps.google.com/maps/preview/@37.726466,-122.409368,16z", "price": "$2500", "available": "available jul 20", "posted": "2017-07-20  8:05pm", "transit": 28, "bicycling": 26, "stanford": 82}, "63": {"url": "http://sfbay.craigslist.org/sfc/apa/6193556942.html", "kind": "apa", "location": "https://maps.google.com/maps/preview/@37.780416,-122.485456,16z", "price": "$2750", "available": "available jul 1", "posted": "2017-06-26  9:33am", "transit": 37, "bicycling": 35, "stanford": 142}, "64": {"url": "http://sfbay.craigslist.org/sfc/apa/6211936127.html", "kind": "apa", "price": "$2200", "available": "available jul 15", "posted": "2017-07-09 12:21pm"}, "65": {"url": "http://sfbay.craigslist.org/sfc/apa/6221113552.html", "kind": "apa", "location": "https://maps.google.com/?q=loc%3A+%36th+Ave+at+Cabrillo%2FFulton+San+Francisco+CA+US", "price": "$2800", "available": "available jul 20", "posted": "2017-07-15  1:21pm", "transit": null, "bicycling": null, "stanford": null}, "66": {"url": "http://sfbay.craigslist.org/sfc/apa/6228804492.html", "kind": "apa", "location": "https://maps.google.com/?q=loc%3A+Taraval+at+%31%38th+Ave+San+Francisco+CA+US", "price": "$2700", "available": "available jul 20", "posted": "2017-07-20  6:27pm", "transit": 46, "bicycling": 47, "stanford": 113}, "67": {"url": "http://sfbay.craigslist.org/pen/apa/6228782495.html", "kind": "apa", "location": "https://maps.google.com/?q=loc%3A+peoria+street+at+roosevelt+street+Daly+City+CA+US", "price": "$2600", "available": "available may 25", "posted": "2017-07-20  6:04pm", "transit": 52, "bicycling": 37, "stanford": 105}, "68": {"url": "http://sfbay.craigslist.org/sfc/apa/6228734946.html", "kind": "apa", "location": "https://maps.google.com/?q=loc%3A+%38%36%30+Corbett+Ave+San+Francisco+CA+US", "price": "$2875", "available": "available jun 24", "posted": "2017-07-20  5:19pm", "transit": 23, "bicycling": 18, "stanford": 107}, "69": {"url": "http://sfbay.craigslist.org/sfc/apa/6228733557.html", "kind": "apa", "location": "https://maps.google.com/?q=loc%3A+%31%32%35+Gardenside+Drive+San+Francisco+CA+US", "price": "$2950", "available": "available jul 20", "posted": "2017-07-20  5:18pm", "transit": 41, "bicycling": 25, "stanford": 104}, "70": {"url": "http://sfbay.craigslist.org/sfc/apa/6206495179.html", "kind": "apa", "location": "https://maps.google.com/?q=loc%3A+%32%33%38+Naglee+Ave+san+francisco+CA+US", "price": "$2350", "available": "available jun 15", "posted": "2017-07-05  7:04pm", "transit": 44, "bicycling": 33, "stanford": 101}, "71": {"url": "http://sfbay.craigslist.org/sfc/apa/6206495990.html", "kind": "apa", "location": "https://maps.google.com/?q=loc%3A+%32%33%38+Naglee+Ave+san+francisco+CA+US", "price": "$2350", "available": "available jun 15", "posted": "2017-07-05  7:04pm", "transit": 44, "bicycling": 33, "stanford": 101}, "72": {"url": "http://sfbay.craigslist.org/sfc/apa/6228631936.html", "kind": "apa", "location": "https://maps.google.com/?q=loc%3A+%32%33%38+Naglee+Ave+san+francisco+CA+US", "price": "$2350", "available": "available jun 15", "posted": "2017-07-20  3:51pm", "transit": 44, "bicycling": 33, "stanford": 101}, "73": {"url": "http://sfbay.craigslist.org/sfc/apa/6228585784.html", "kind": "apa", "location": "https://maps.google.com/maps/preview/@37.745000,-122.438300,16z", "price": "$2200", "available": "available jul 20", "posted": "2017-07-20  3:16pm", "transit": 0, "bicycling": 22, "stanford": 104}, "74": {"url": "http://sfbay.craigslist.org/sfc/apa/6224064363.html", "kind": "apa", "location": "https://maps.google.com/?q=loc%3A+%32%31%36%33+%34%34th+Avenue+San+Francisco+CA+US", "price": "$2975", "available": "available aug 1", "posted": "2017-07-17  3:20pm", "transit": 60, "bicycling": 43, "stanford": 160}, "75": {"url": "http://sfbay.craigslist.org/sfc/apa/6219296024.html", "kind": "apa", "price": "$1500", "available": "available jul 21", "posted": "2017-07-14 10:09am"}, "76": {"url": "http://sfbay.craigslist.org/sfc/apa/6219348222.html", "kind": "apa", "location": "https://maps.google.com/maps/preview/@37.716610,-122.455444,16z", "price": "$2995", "available": "available jul 15", "posted": "2017-07-14 10:39am", "transit": 44, "bicycling": 36, "stanford": 95}, "77": {"url": "http://sfbay.craigslist.org/sfc/apa/6191369420.html", "kind": "apa", "location": "https://maps.google.com/?q=loc%3A+Moraga+at+%33%30th+Ave+San+Francisco+CA+US", "price": "$2500", "available": "available jun 21", "posted": "2017-06-24  1:36pm", "transit": 63, "bicycling": 37, "stanford": 140}, "78": {"url": "http://sfbay.craigslist.org/sfc/apa/6206147448.html", "kind": "apa", "location": "https://maps.google.com/maps/preview/@37.759300,-122.483600,16z", "price": "$2700", "available": "available jul 5", "posted": "2017-07-05  2:26pm", "transit": 48, "bicycling": 35, "stanford": 112}, "79": {"url": "http://sfbay.craigslist.org/sfc/apa/6211059732.html", "kind": "apa", "location": "https://maps.google.com/?q=loc%3A+%33%33%36+Vallejo+St%2E+San+Francisco+CA+US", "price": "$2150", "available": "available aug 1", "posted": "2017-07-08  6:33pm", "transit": 27, "bicycling": 18, "stanford": 100}, "80": {"url": "http://sfbay.craigslist.org/sfc/apa/6219491235.html", "kind": "apa", "location": "https://maps.google.com/?q=loc%3A+%34%32%33+%33%34th+Avenue%2C+at+Clement+Street+San+Francisco+CA+US", "price": "$2800", "available": "available jun 2", "posted": "2017-07-14 12:02pm", "transit": 60, "bicycling": 43, "stanford": 160}, "81": {"url": "http://sfbay.craigslist.org/sfc/apa/6228188523.html", "kind": "apa", "location": "https://maps.google.com/?q=loc%3A+%32%32%37+Randolph+Street+San+Francisco+CA+US", "price": "$2500", "available": "available jul 20", "posted": "2017-07-20 10:54am", "transit": 46, "bicycling": 42, "stanford": 101}, "82": {"url": "http://sfbay.craigslist.org/sfc/apa/6228175621.html", "kind": "apa", "location": "https://maps.google.com/?q=loc%3A+Lucy+San+Francisco+CA+US", "price": "$2750", "available": "available jul 20", "posted": "2017-07-20 10:46am", "transit": 34, "bicycling": 21, "stanford": 83}, "83": {"url": "http://sfbay.craigslist.org/sfc/apa/6228127850.html", "kind": "apa", "location": "https://maps.google.com/?q=loc%3A+grafton+at+lee+san+francisco+CA+US", "price": "$2800", "available": "available jul 20", "posted": "2017-07-20 10:17am", "transit": 36, "bicycling": 33, "stanford": 91}, "84": {"url": "http://sfbay.craigslist.org/sfc/apa/6219749503.html", "kind": "apa", "location": "https://maps.google.com/?q=loc%3A+Greenwich+at+Scott+San+Francisco+CA+US", "price": "$2450", "available": "available aug 1", "posted": "2017-07-14  2:46pm", "transit": 38, "bicycling": 27, "stanford": 152}, "85": {"url": "http://sfbay.craigslist.org/sfc/apa/6228093377.html", "kind": "apa", "location": "https://maps.google.com/?q=loc%3A+Sacramento+Street+at+Franklin+Street+San+Francisco+CA+US", "price": "$2000", "available": "available jul 20", "posted": "2017-07-20  9:57am", "transit": 29, "bicycling": 16, "stanford": 106}, "86": {"url": "http://sfbay.craigslist.org/sfc/apa/6228080009.html", "kind": "apa", "location": "https://maps.google.com/?q=loc%3A+%36%36%34+Natoma+Street+San+Francisco+CA+US", "price": "$1850", "available": "available jun 5", "posted": "2017-07-20  9:49am", "transit": 18, "bicycling": 14, "stanford": 56}, "87": {"url": "http://sfbay.craigslist.org/pen/apa/6228056214.html", "kind": "apa", "location": "https://maps.google.com/?q=loc%3A+%31%37%31%31+Hampton+Lane+Daly+City+CA+US", "price": "$3000", "available": "available aug 15", "posted": "2017-07-20  9:35am", "transit": 65, "bicycling": 39, "stanford": 116}, "88": {"url": "http://sfbay.craigslist.org/sfc/apa/6228045865.html", "kind": "apa", "location": "https://maps.google.com/?q=loc%3A+%34%36th+Avenue+at+vicente+and+wawona+San+Francisco+CA+US", "price": "$2380", "available": "available jul 21", "posted": "2017-07-20  9:29am", "transit": 69, "bicycling": 122, "stanford": 56}, "89": {"url": "http://sfbay.craigslist.org/sfc/apa/6224231882.html", "kind": "apa", "location": "https://maps.google.com/maps/preview/@37.719298,-122.390020,16z", "price": "$2400", "available": "available aug 1", "posted": "2017-07-17  5:29pm", "transit": 31, "bicycling": 25, "stanford": 86}, "90": {"url": "http://sfbay.craigslist.org/sfc/apa/6221112646.html", "kind": "apa", "location": "https://maps.google.com/?q=loc%3A+%36th+Ave+at+Cabrillo%2FFulton+San+Francisco+CA+US", "price": "$2800", "available": "available jul 20", "posted": "2017-07-15  1:20pm", "transit": null, "bicycling": null, "stanford": null}, "91": {"url": "http://sfbay.craigslist.org/sfc/apa/6223999597.html", "kind": "apa", "location": "https://maps.google.com/?q=loc%3A+%37th+Ave+at+Anza+St+San+Francisco+CA+US", "price": "$2900", "available": "available jul 1", "posted": "2017-07-17  2:37pm", "transit": 55, "bicycling": 41, "stanford": 154}, "92": {"url": "http://sfbay.craigslist.org/pen/apa/6214211290.html", "kind": "apa", "location": "https://maps.google.com/?q=loc%3A+lausanne+at+Hillside+Daly+City+CA+US", "price": "$2775", "available": "available aug 1", "posted": "2017-07-11 12:31am", "transit": 59, "bicycling": 45, "stanford": 94}, "93": {"url": "http://sfbay.craigslist.org/sfc/apa/6198763034.html", "kind": "apa", "location": "https://maps.google.com/?q=loc%3A+%35%32+gambier+street+San+Francisco+CA+US", "price": "$2900", "available": "available jun 10", "posted": "2017-06-30  2:01am", "transit": 9, "bicycling": 24, "stanford": 78}, "94": {"url": "http://sfbay.craigslist.org/sfc/apa/6227554612.html", "kind": "apa", "location": "https://maps.google.com/?q=loc%3A+%32+Townsend+Street+San+Francisco+CA+US", "price": "$1300", "available": "available aug 1", "posted": "2017-07-19 11:59pm", "transit": 12, "bicycling": 9, "stanford": 50}, "95": {"url": "http://sfbay.craigslist.org/sfc/apa/6222515463.html", "kind": "apa", "location": "https://maps.google.com/?q=loc%3A+%32%30th+Ave+at+Judah+San+Francisco+CA+US", "price": "$2460", "available": "available aug 5", "posted": "2017-07-16  2:37pm", "transit": 65, "bicycling": 40, "stanford": 151}, "96": {"url": "http://sfbay.craigslist.org/sfc/apa/6214011533.html", "kind": "apa", "location": "https://maps.google.com/?q=loc%3A+%33rd+Avenue+at+Anza+San+Francisco+CA+US", "price": "$1450", "available": "available jul 1", "posted": "2017-07-10  7:03pm", "transit": 53, "bicycling": 39, "stanford": 151}, "97": {"url": "http://sfbay.craigslist.org/sfc/apa/6227440591.html", "kind": "apa", "location": "https://maps.google.com/?q=loc%3A+%31%33%30%30+Kirkham+Street+San+Francisco+CA+US", "price": "$3000", "available": "available jul 19", "posted": "2017-07-19  8:28pm", "transit": 43, "bicycling": 26, "stanford": 116}, "98": {"url": "http://sfbay.craigslist.org/sfc/apa/6227438755.html", "kind": "apa", "location": "https://maps.google.com/?q=loc%3A+%32%39th+ave+at+Kirkham+San+Francisco+CA+US", "price": "$2500", "available": "available jul 20", "posted": "2017-07-19  8:25pm", "transit": 56, "bicycling": 44, "stanford": 148}, "99": {"url": "http://sfbay.craigslist.org/sfc/apa/6216604051.html", "kind": "apa", "location": "https://maps.google.com/?q=loc%3A+alabama+at+precita+san+francisco+CA+US", "price": "$3000", "available": "available jul 15", "posted": "2017-07-12  1:01pm", "transit": 20, "bicycling": 13, "stanford": 89}, "100": {"url": "http://sfbay.craigslist.org/sfc/apa/6208030733.html", "kind": "apa", "location": "https://maps.google.com/?q=loc%3A+%37th+Avenue+at+Cabrillo+San+Francisco+CA+US", "price": "$3000", "available": "available jun 15", "posted": "2017-07-06  6:47pm", "transit": 50, "bicycling": 40, "stanford": 154}, "101": {"url": "http://sfbay.craigslist.org/sfc/apa/6227157649.html", "kind": "apa", "location": "https://maps.google.com/maps/preview/@37.713855,-122.443421,16z", "price": "$2100", "available": "available jul 10", "posted": "2017-07-19  3:54pm", "transit": 45, "bicycling": 32, "stanford": 94}, "102": {"url": "http://sfbay.craigslist.org/sfc/apa/6227142818.html", "kind": "apa", "location": "https://maps.google.com/?q=loc%3A+%32%33%38+Naglee+Ave+san+francisco+CA+US", "price": "$2350", "available": "available jun 15", "posted": "2017-07-19  3:42pm", "transit": 44, "bicycling": 33, "stanford": 101}, "103": {"url": "http://sfbay.craigslist.org/sfc/apa/6227142578.html", "kind": "apa", "location": "https://maps.google.com/?q=loc%3A+%32%33%38+Naglee+Ave+san+francisco+CA+US", "price": "$2350", "available": "available jun 15", "posted": "2017-07-19  3:42pm", "transit": 45, "bicycling": 33, "stanford": 101}, "104": {"url": "http://sfbay.craigslist.org/sfc/apa/6218755164.html", "kind": "apa", "location": "https://maps.google.com/?q=loc%3A+%33%39th+ave+san+franisco+CA+US", "price": "$2900", "available": "available jul 13", "posted": "2017-07-14 12:48am", "transit": 56, "bicycling": 44, "stanford": 148}, "105": {"url": "http://sfbay.craigslist.org/sfc/apa/6227021096.html", "kind": "apa", "location": "https://maps.google.com/?q=loc%3A+%39%36%35+Geary+Street+San+Francisco+CA+US", "price": "$2800", "available": "available jul 19", "posted": "2017-07-19  2:15pm", "transit": 25, "bicycling": 15, "stanford": 95}, "106": {"url": "http://sfbay.craigslist.org/sfc/apa/6226883593.html", "kind": "apa", "location": "https://maps.google.com/?q=loc%3A+%31%32th+ave+at+Irving+San+Francisco+CA+US", "price": "$3000", "available": "available apr 1", "posted": "2017-07-19 12:47pm", "transit": 66, "bicycling": 40, "stanford": 157}, "107": {"url": "http://sfbay.craigslist.org/sfc/apa/6226823188.html", "kind": "apa", "location": "https://maps.google.com/?q=loc%3A+belle+at+st%2E+charles+san+francisco+CA+US", "price": "$2200", "available": "available jul 19", "posted": "2017-07-19 12:10pm", "transit": 34, "bicycling": 44, "stanford": 82}}}